desafe.py
desafe-1.0.6.dist-info/LICENSE
desafe-1.0.6.dist-info/METADATA
desafe-1.0.6.dist-info/WHEEL
desafe-1.0.6.dist-info/entry_points.txt
desafe-1.0.6.dist-info/top_level.txt
desafe-1.0.6.dist-info/zip-safe
desafe-1.0.6.dist-info/RECORD
