Metadata-Version: 2.1
Name: desafe
Version: 1.0.6
Summary: An utility to decrypt Safe in Cloud password files
Home-page: https://github.com/joncastro/SafeInCloud
Author: pjon
License: LICENSE
Classifier: Development Status :: 3 - Alpha
Classifier: Environment :: Console
Classifier: Intended Audience :: Developers
Classifier: Intended Audience :: System Administrators
Classifier: Intended Audience :: End Users/Desktop
Classifier: Programming Language :: Python
Classifier: Programming Language :: Python :: 2
Classifier: Programming Language :: Python :: 2.6
Classifier: Programming Language :: Python :: 2.7
Classifier: Topic :: Security :: Cryptography
Classifier: Topic :: Utilities
Classifier: License :: OSI Approved :: Apache Software License
Classifier: Operating System :: POSIX :: Linux
Classifier: Operating System :: MacOS
License-File: LICENSE
Requires-Dist: docopt
Requires-Dist: passlib
Requires-Dist: pycryptodomex
Requires-Dist: xmltodict
